elk/__init__.py
elk/_version.py
elk/catalogue.py
elk/cli.py
elk/elk.conf
elk/elk.py
elk/exceptions.py
elk/projection.py
elk/waveform.py
elk_waveform-0.13.dist-info/AUTHORS.rst
elk_waveform-0.13.dist-info/LICENSE
elk_waveform-0.13.dist-info/METADATA
elk_waveform-0.13.dist-info/WHEEL
elk_waveform-0.13.dist-info/entry_points.txt
elk_waveform-0.13.dist-info/top_level.txt
elk_waveform-0.13.dist-info/zip-safe
elk_waveform-0.13.dist-info/RECORD
