Metadata-Version: 2.1
Name: elk-waveform
Version: 0.13
Summary: A Python package for managing and interacting with gravitational waveform catalogues.
Home-page: https://github.com/transientlunatic/elk
Author: Daniel Williams
Author-email: daniel.williams@ligo.org
License: MIT license
Keywords: elk
Platform: UNKNOWN
Classifier: Development Status :: 2 - Pre-Alpha
Classifier: Intended Audience :: Developers
Classifier: License :: OSI Approved :: MIT License
Classifier: Natural Language :: English
Classifier: Programming Language :: Python :: 3
Classifier: Programming Language :: Python :: 3.6
Classifier: Programming Language :: Python :: 3.7
License-File: LICENSE
License-File: AUTHORS.rst
Requires-Dist: numpy
Requires-Dist: pandas
Requires-Dist: lalsuite
Requires-Dist: pycbc
